[
  {
    "abbrev":"PC 08",
    "source":"bhūtārocanasikkhāpadaṃ",
    "sentence":"yo pana bhikkhu anupasampannassa uttarimanussadhammaṃ āroceyya, bhūtasmiṃ pācittiyaṃ.",
    "pali_1":"yo",
    "pos":"pron",
    "grammar":"masc nom sg of ya",
    "case":"",
    "meaning":"whichever, whoever",
    "meaning_lit":"",
    "root":"",
    "base":"",
    "construction":"",
    "compound_type":"",
    "compound_construction":""
  },
  {
    "abbrev":"PC 08",
    "source":"bhūtārocanasikkhāpadaṃ",
    "sentence":"yo pana bhikkhu anupasampannassa uttarimanussadhammaṃ āroceyya, bhūtasmiṃ pācittiyaṃ.",
    "pali_1":"pana",
    "pos":"ind",
    "grammar":"",
    "case":"",
    "meaning":"then, now, so, but",
    "meaning_lit":"",
    "root":"",
    "base":"",
    "construction":"",
    "compound_type":"",
    "compound_construction":""
  },
  {
    "abbrev":"PC 08",
    "source":"bhūtārocanasikkhāpadaṃ",
    "sentence":"yo pana bhikkhu anupasampannassa uttarimanussadhammaṃ āroceyya, bhūtasmiṃ pācittiyaṃ.",
    "pali_1":"bhikkhu",
    "pos":"noun",
    "grammar":"masc nom sg, from bhikkhati, comp",
    "case":"",
    "meaning":"monk, monastic",
    "meaning_lit":"beggar, mendicant",
    "root":"√bhikkh (beg)",
    "base":"",
    "construction":"√bhikkh + u",
    "compound_type":"",
    "compound_construction":""
  },
  {
    "abbrev":"PC 08",
    "source":"bhūtārocanasikkhāpadaṃ",
    "sentence":"yo pana bhikkhu anupasampannassa uttarimanussadhammaṃ āroceyya, bhūtasmiṃ pācittiyaṃ.",
    "pali_1":"anupasampannassa",
    "pos":"noun",
    "grammar":"masc dat sg of anupasampanna",
    "case":"",
    "meaning":"to an unordained person",
    "meaning_lit":"not accomplished",
    "root":"√pad (go, step)",
    "base":"",
    "construction":"na + upa + saṃ + √pad + na",
    "compound_type":"",
    "compound_construction":""
  },
  {
    "abbrev":"PC 08",
    "source":"bhūtārocanasikkhāpadaṃ",
    "sentence":"yo pana bhikkhu anupasampannassa uttarimanussadhammaṃ āroceyya, bhūtasmiṃ pācittiyaṃ.",
    "pali_1":"uttarimanussadhammaṃ",
    "pos":"noun",
    "grammar":"masc acc sg of uttarimanussadhamma, comp",
    "case":"",
    "meaning":"superior than human state, superhuman state",
    "meaning_lit":"higher than human state",
    "root":"",
    "base":"",
    "construction":"uttari + manussadhamma",
    "compound_type":"kammadhāraya",
    "compound_construction":"uttari + manussadhamma\n(or)\nuttarimanussa + dhamma"
  },
  {
    "abbrev":"PC 08",
    "source":"bhūtārocanasikkhāpadaṃ",
    "sentence":"yo pana bhikkhu anupasampannassa uttarimanussadhammaṃ āroceyya, bhūtasmiṃ pācittiyaṃ.",
    "pali_1":"āroceyya",
    "pos":"verb",
    "grammar":"opt 3rd sg of āroceti",
    "case":"+acc",
    "meaning":"he would state, announce, declare",
    "meaning_lit":"",
    "root":"√ruc (shine, approve)",
    "base":"√ruc + *e > roce",
    "construction":"ā + roce + ti",
    "compound_type":"",
    "compound_construction":""
  },
  {
    "abbrev":"PC 08",
    "source":"bhūtārocanasikkhāpadaṃ",
    "sentence":"yo pana bhikkhu anupasampannassa uttarimanussadhammaṃ āroceyya, bhūtasmiṃ pācittiyaṃ.",
    "pali_1":"bhūtasmiṃ",
    "pos":"pp",
    "grammar":"masc loc sg of bhūta",
    "case":"",
    "meaning":"when true; when accurate",
    "meaning_lit":"in what is",
    "root":"√bhū (be)",
    "base":"",
    "construction":"√bhū + ta",
    "compound_type":"",
    "compound_construction":""
  },
  {
    "abbrev":"PC 08",
    "source":"bhūtārocanasikkhāpadaṃ",
    "sentence":"yo pana bhikkhu anupasampannassa uttarimanussadhammaṃ āroceyya, bhūtasmiṃ pācittiyaṃ.",
    "pali_1":"pācittiyaṃ",
    "pos":"noun",
    "grammar":"nt nom sg of pācittiya",
    "case":"+loc",
    "meaning":"offence requiring confession, offence involving expiation",
    "meaning_lit":"",
    "root":"",
    "base":"",
    "construction":"",
    "compound_type":"",
    "compound_construction":""
  },
  {
    "abbrev":"PC 08",
    "source":"bhūtārocanasikkhāpadaṃ",
    "sentence":"yo pana bhikkhu anupasampannassa uttarimanussadhammaṃ āroceyya, bhūtasmiṃ pācittiyaṃ.",
    "pali_1":"If any monk should declare a superhuman state to an unordained person, when true, there is an offence requiring confession.\n",
    "pos":"",
    "grammar":"",
    "case":"",
    "meaning":"",
    "meaning_lit":"",
    "root":"",
    "base":"",
    "construction":"",
    "compound_type":"",
    "compound_construction":""
  }
]